ml_fashion_cnn/__init__.py
ml_fashion_cnn/text_reader.py
ml_fashion_cnn/data/my_code.py
ml_fashion_cnn-0.1.dist-info/METADATA
ml_fashion_cnn-0.1.dist-info/WHEEL
ml_fashion_cnn-0.1.dist-info/top_level.txt
ml_fashion_cnn-0.1.dist-info/RECORD
