Metadata-Version: 2.1
Name: ml-fashion-cnn
Version: 0.1
Summary: Code for fashion MNIST using CNN
Home-page: https://github.com/savioratharv/prac_testing
Author: davinci003
Author-email: freegpt00@gmail.com
